rayserverdl/version.py
ryserverdl-1.0.0.dist-info/LICENSE
ryserverdl-1.0.0.dist-info/METADATA
ryserverdl-1.0.0.dist-info/WHEEL
ryserverdl-1.0.0.dist-info/top_level.txt
ryserverdl-1.0.0.dist-info/zip-safe
ryserverdl-1.0.0.dist-info/RECORD
